brother_printer_fwupd-0.8.0.dist-info/METADATA
brother_printer_fwupd-0.8.0.dist-info/WHEEL
brother_printer_fwupd-0.8.0.dist-info/entry_points.txt
brother_printer_fwupd-0.8.0.dist-info/licenses/LICENSE
brother_printer_fwupd/__init__.py
brother_printer_fwupd/__main__.py
brother_printer_fwupd/autodiscovery.py
brother_printer_fwupd/common.py
brother_printer_fwupd/firmware_downloader.py
brother_printer_fwupd/firmware_uploader.py
brother_printer_fwupd/models.py
brother_printer_fwupd/snmp_info.py
brother_printer_fwupd/utils.py
brother_printer_fwupd-0.8.0.dist-info/RECORD
