Metadata-Version: 2.1
Name: brother_printer_fwupd
Version: 0.8.0
Summary: Script to update the firmware of some Brother printers (e. g. MFC).
Author-Email: sedrubal <dev@sedrubal.de>
License: GPL-3.0-or-later
Project-URL: repository, https://github.com/sedrubal/brother_printer_fwupd.git
Requires-Python: <4.0,>=3.9
Requires-Dist: requests>=2.32.3
Requires-Dist: beautifulsoup4>=4.12.3
Requires-Dist: lxml>=5.3.0
Requires-Dist: termcolor>=2.5.0
Requires-Dist: pysnmp>=7.1.15
Provides-Extra: autodiscover
Requires-Dist: zeroconf<1.0.0,>=0.136.0; extra == "autodiscover"
